[
    {
        "11/10/2024-PHYSICS-101": {
            "Avg_of_test": 14,
            "Avg_of_student_chapter_wise": {
                "Units and Measurements (PUC-I)": 0,
                "Motion in a Straight Line (PUC-I)": 0,
                "Motion in a Plane (PUC-I)": 0,
                "Laws of Motion (PUC-I)": 100,
                "Work, Energy and Power (PUC-I)": 61,
                "System of Particles and Rotational Motion (PUC-I)": 0,
                "Gravitation (PUC-I)": 0,
                "Mechanical Properties of Solids (PUC-I)": 0,
                "Mechanical Properties of Fluids (PUC-I)": 100,
                "Thermal Properties of Matter (PUC-I)": 0,
                "Thermodynamics (PUC-I)": 0,
                "Kinetic Theory (PUC-I)": 0,
                "Oscillations (PUC-I)": 0,
                "Waves (PUC-I)": 0,
                "Electric Charges and Fields (PUC-II)": 0,
                "Electrostatic Potential and Capacitance (PUC-II)": 46,
                "Current Electricity (PUC-II)": 82,
                "Moving charges and magnetism (PUC-II)": 0,
                "Magnetism and Matter (PUC-II)": 0,
                "Electromagnetic Induction (PUC-II)": 0,
                "Alternating Current (PUC-II)": 0,
                "Electromagnetic Waves (PUC-II)": 0,
                "Ray Optics and Optical Instruments (PUC-II)": 0,
                "Wave Optics (PUC-II)": 0,
                "Dual Nature of Radiation and Matter (PUC-II)": 0,
                "Atoms (PUC-II)": 0,
                "Nuclei (PUC-II)": 0,
                "Semiconductor Electronics Materials, Devices and Simple Circuits (PUC-II)": 0
            },
            "Max_marks_chapter_wise": {
                "Laws of Motion (PUC-I)": [
                    100,
                    "11/10/2024",
                    101
                ],
                "Work, Energy and Power (PUC-I)": [
                    61,
                    "11/10/2024",
                    101
                ],
                "Mechanical Properties of Fluids (PUC-I)": [
                    100,
                    "11/10/2024",
                    101
                ],
                "Electrostatic Potential and Capacitance (PUC-II)": [
                    46,
                    "11/10/2024",
                    101
                ],
                "Current Electricity (PUC-II)": [
                    82,
                    "11/10/2024",
                    101
                ]
            },
            "Max_marks_in_current_test": {
                "2-100": [
                    "Laws of Motion (PUC-I)",
                    "Mechanical Properties of Fluids (PUC-I)"
                ]
            }
        }
    },
    {
        "15/10/2024-PHYSICS-102": {
            "Avg_of_test": 18,
            "Avg_of_student_chapter_wise": {
                "Units and Measurements (PUC-I)": 0,
                "Motion in a Straight Line (PUC-I)": 36,
                "Motion in a Plane (PUC-I)": 0,
                "Laws of Motion (PUC-I)": 50,
                "Work, Energy and Power (PUC-I)": 30,
                "System of Particles and Rotational Motion (PUC-I)": 23,
                "Gravitation (PUC-I)": 0,
                "Mechanical Properties of Solids (PUC-I)": 0,
                "Mechanical Properties of Fluids (PUC-I)": 50,
                "Thermal Properties of Matter (PUC-I)": 0,
                "Thermodynamics (PUC-I)": 0,
                "Kinetic Theory (PUC-I)": 0,
                "Oscillations (PUC-I)": 0,
                "Waves (PUC-I)": 0,
                "Electric Charges and Fields (PUC-II)": 0,
                "Electrostatic Potential and Capacitance (PUC-II)": 53,
                "Current Electricity (PUC-II)": 41,
                "Moving charges and magnetism (PUC-II)": 41,
                "Magnetism and Matter (PUC-II)": 0,
                "Electromagnetic Induction (PUC-II)": 0,
                "Alternating Current (PUC-II)": 0,
                "Electromagnetic Waves (PUC-II)": 0,
                "Ray Optics and Optical Instruments (PUC-II)": 0,
                "Wave Optics (PUC-II)": 30,
                "Dual Nature of Radiation and Matter (PUC-II)": 50,
                "Atoms (PUC-II)": 0,
                "Nuclei (PUC-II)": 50,
                "Semiconductor Electronics Materials, Devices and Simple Circuits (PUC-II)": 50
            },
            "Max_marks_chapter_wise": {
                "Motion in a Straight Line (PUC-I)": [
                    71,
                    "15/10/2024",
                    102
                ],
                "Laws of Motion (PUC-I)": [
                    100,
                    "11/10/2024",
                    101
                ],
                "Work, Energy and Power (PUC-I)": [
                    61,
                    "11/10/2024",
                    101
                ],
                "System of Particles and Rotational Motion (PUC-I)": [
                    46,
                    "15/10/2024",
                    102
                ],
                "Mechanical Properties of Fluids (PUC-I)": [
                    100,
                    "11/10/2024",
                    101
                ],
                "Electrostatic Potential and Capacitance (PUC-II)": [
                    60,
                    "15/10/2024",
                    102
                ],
                "Current Electricity (PUC-II)": [
                    82,
                    "11/10/2024",
                    101
                ],
                "Moving charges and magnetism (PUC-II)": [
                    82,
                    "15/10/2024",
                    102
                ],
                "Wave Optics (PUC-II)": [
                    61,
                    "15/10/2024",
                    102
                ],
                "Dual Nature of Radiation and Matter (PUC-II)": [
                    100,
                    "15/10/2024",
                    102
                ],
                "Nuclei (PUC-II)": [
                    100,
                    "15/10/2024",
                    102
                ],
                "Semiconductor Electronics Materials, Devices and Simple Circuits (PUC-II)": [
                    100,
                    "15/10/2024",
                    102
                ]
            },
            "Max_marks_in_current_test": {
                "1-53": [
                    "Electrostatic Potential and Capacitance (PUC-II)"
                ]
            }
        }
    }
]